[
    {
        "id": 1,
        "name": "Company A",
        "address": "123 Main St",
        "phone": "123-456-7890"
    },
    {
        "id": 2,
        "name": "Company B",
        "address": "456 Elm St",
        "phone": "123-456-7891"
    },
    {
        "id": 3,
        "name": "Company C",
        "address": "789 Oak St",
        "phone": "123-456-7892"
    },
    {
        "id": 4,
        "name": "Company D",
        "address": "101 Pine St",
        "phone": "123-456-7893"
    },
    {
        "id": 5,
        "name": "Company E",
        "address": "102 Maple St",
        "phone": "123-456-7894"
    },
    {
        "id": 6,
        "name": "Company F",
        "address": "103 Cedar St",
        "phone": "123-456-7895"
    },
    {
        "id": 7,
        "name": "Company G",
        "address": "104 Birch St",
        "phone": "123-456-7896"
    },
    {
        "id": 8,
        "name": "Company H",
        "address": "105 Willow St",
        "phone": "123-456-7897"
    },
    {
        "id": 9,
        "name": "Company I",
        "address": "106 Cherry St",
        "phone": "123-456-7898"
    },
    {
        "id": 10,
        "name": "Company J",
        "address": "107 Walnut St",
        "phone": "123-456-7899"
    }
]